dash_split/Split.py
dash_split/__init__.py
dash_split/_imports_.py
dash_split/dash_split.min.js
dash_split/dash_split.min.js.map
dash_split/metadata.json
dash_split/package-info.json
dash_split/split.css
dash_split-0.0.4.dist-info/LICENSE
dash_split-0.0.4.dist-info/METADATA
dash_split-0.0.4.dist-info/WHEEL
dash_split-0.0.4.dist-info/top_level.txt
dash_split-0.0.4.dist-info/RECORD
