Metadata-Version: 2.1
Name: dash-split
Version: 0.0.4
Summary: Dash wrapper for split.js
Home-page: https://github.com/TCatshoek/dash-split
Author: Tom Catshoek <tomcatshoek@zeelandnet.nl>
License: MIT
Platform: UNKNOWN
Classifier: Framework :: Dash
License-File: LICENSE
